appointment/__init__.py
appointment/admin.py
appointment/apps.py
appointment/forms.py
appointment/static/css/appointment/bethany_ds.css
appointment/static/css/appointment/medicio_ds.css
appointment/static/css/appointment/medilab_ds.css
appointment/static/css/appointment/mentor_ds.css
appointment/templates/appointment/_common.html
appointment/templates/appointment/bethany_ds.html
appointment/templates/appointment/medicio_ds.html
appointment/templates/appointment/medilab_ds.html
appointment/templates/appointment/mentor_ds.html
appointment/templatetags/__init__.py
appointment/templatetags/appointment_tags.py
django_appointment_ds-0.1.5.dist-info/LICENSE
django_appointment_ds-0.1.5.dist-info/METADATA
django_appointment_ds-0.1.5.dist-info/WHEEL
django_appointment_ds-0.1.5.dist-info/top_level.txt
django_appointment_ds-0.1.5.dist-info/RECORD
